MANIFEST.in
create_glidein_tarball.py
setup.py
pyglidein/__init__.py
pyglidein/client.py
pyglidein/client_metrics.py
pyglidein/client_util.py
pyglidein/config.py
pyglidein/glidein_start.sh
pyglidein/log_shipper.sh
pyglidein/metrics_sender_client.py
pyglidein/os_arch.sh
pyglidein/server.py
pyglidein/ssh_helper.py
pyglidein/submit.py
pyglidein/util.py
pyglidein.egg-info/PKG-INFO
pyglidein.egg-info/SOURCES.txt
pyglidein.egg-info/dependency_links.txt
pyglidein.egg-info/entry_points.txt
pyglidein.egg-info/requires.txt
pyglidein.egg-info/top_level.txt
pyglidein/etc/client_defaults.cfg
pyglidein/startd_cron_scripts/clsim_gpu_test.py
pyglidein/startd_cron_scripts/cvmfs_test.py
pyglidein/startd_cron_scripts/gridftp_test.py
pyglidein/startd_cron_scripts/post_cvmfs.sh
pyglidein/startd_cron_scripts/pre_cvmfs.sh