Metadata-Version: 1.2
Name: pyglidein
Version: 1.1.0
Summary: Some python scripts to launch HTCondor glideins
Home-page: https://github.com/WIPACrepo/pyglidein
Author: WIPAC
Author-email: contact-us@icecube.wisc.edu
License: UNKNOWN
Keywords: htcondor dHTC glidein
Platform: UNKNOWN
Classifier: Programming Language :: Python :: 2
Classifier: Programming Language :: Python :: 2.6
Classifier: Programming Language :: Python :: 2.7
Classifier: Programming Language :: Python :: 3
Classifier: Programming Language :: Python :: 3.3
Classifier: Programming Language :: Python :: 3.4
Classifier: Programming Language :: Python :: 3.5
Requires-Python: >=2.6
